changelog_api_client-1.0.1.dist-info/licenses/LICENSE
changelog_api_client-1.0.1.dist-info/licenses/NOTICE
e1004/changelog_api_client/__init__.py
e1004/changelog_api_client/cli.py
e1004/changelog_api_client/cli_client.py
e1004/changelog_api_client/client.py
e1004/changelog_api_client/create_change.py
e1004/changelog_api_client/create_version.py
e1004/changelog_api_client/delete_change.py
e1004/changelog_api_client/delete_version.py
e1004/changelog_api_client/errors.py
e1004/changelog_api_client/model.py
e1004/changelog_api_client/move_change.py
e1004/changelog_api_client/py.typed
e1004/changelog_api_client/read_changes.py
e1004/changelog_api_client/read_versions.py
e1004/changelog_api_client/release_version.py
changelog_api_client-1.0.1.dist-info/METADATA
changelog_api_client-1.0.1.dist-info/WHEEL
changelog_api_client-1.0.1.dist-info/entry_points.txt
changelog_api_client-1.0.1.dist-info/top_level.txt
changelog_api_client-1.0.1.dist-info/RECORD
