Metadata-Version: 2.4
Name: changelog-api-client
Version: 1.0.1
Summary: API client for Changelog API
License: Apache-2.0
Project-URL: Repository, https://github.com/e1004/changelog-api-client
Requires-Python: >=3.11
License-File: LICENSE
License-File: NOTICE
Requires-Dist: requests==2.*
Requires-Dist: realerikrani-projectclient==1.*
Requires-Dist: realerikrani-baseclient==1.*
Dynamic: license-file
